nessvector/__init__.py
nessvector-1.0.0.dist-info/entry_points.txt
nessvector-1.0.0.dist-info/WHEEL
nessvector-1.0.0.dist-info/METADATA
nessvector-1.0.0.dist-info/RECORD
