Metadata-Version: 2.1
Name: nessvector
Version: 1.0.0
Summary: Alias that redirects to nessvec
Home-page: https://gitlab.com/tangibleai/nessvec
License: AGPL3
Keywords: NLP,Natural Language Processing,Virtual Assistant,chatbot,Text Processing,Machine Learning,Text Mining,Deep Learning
Author: Hobson Lane
Author-email: hobson@tangibleai.com
Requires-Python: >=3.7,<3.10
Classifier: Development Status :: 5 - Production/Stable
Classifier: Intended Audience :: Developers
Classifier: License :: OSI Approved :: GNU Affero General Public License v3
Classifier: License :: Other/Proprietary License
Classifier: Operating System :: OS Independent
Classifier: Programming Language :: Python :: 3
Classifier: Programming Language :: Python :: 3.7
Classifier: Programming Language :: Python :: 3.8
Classifier: Programming Language :: Python :: 3.9
Classifier: Topic :: Software Development :: Libraries :: Python Modules
Classifier: Topic :: Text Processing :: Linguistic
Requires-Dist: nessvec (>=0.0.18,<0.0.19)
Project-URL: Documentation, https://gitlab.com/tangibleai/nessvec
Project-URL: Repository, https://gitlab.com/tangibleai/nessvec
